mps_correlation/_C.cpython-314-darwin.so
mps_correlation/__init__.py
mps_correlation/csrc/correlation_mps.mm
mps_correlation-0.1.4.dist-info/METADATA
mps_correlation-0.1.4.dist-info/WHEEL
mps_correlation-0.1.4.dist-info/top_level.txt
mps_correlation-0.1.4.dist-info/RECORD
