Metadata-Version: 2.4
Name: mps-correlation
Version: 0.1.4
Summary: Correlation layer for optical flow on Apple Silicon (MPS)
Author: mpsops
License-Expression: MIT
Project-URL: Homepage, https://github.com/mpsops/mps-correlation
Project-URL: Repository, https://github.com/mpsops/mps-correlation
Project-URL: Issues, https://github.com/mpsops/mps-correlation/issues
Keywords: correlation,optical-flow,raft,pwc-net,flownet,apple-silicon,pytorch,mps,metal
Classifier: Development Status :: 3 - Alpha
Classifier: Intended Audience :: Developers
Classifier: Intended Audience :: Science/Research
Classifier: Operating System :: MacOS :: MacOS X
Classifier: Programming Language :: Python :: 3
Classifier: Programming Language :: Python :: 3.10
Classifier: Programming Language :: Python :: 3.11
Classifier: Programming Language :: Python :: 3.12
Classifier: Topic :: Scientific/Engineering :: Artificial Intelligence
Requires-Python: >=3.10
Requires-Dist: torch>=2.0.0
Dynamic: requires-python
